DeeType/__init__.py
DeeType/main.py
DeeType-0.3.dist-info/LICENSE
DeeType-0.3.dist-info/METADATA
DeeType-0.3.dist-info/WHEEL
DeeType-0.3.dist-info/top_level.txt
DeeType-0.3.dist-info/RECORD
