Metadata-Version: 2.1
Name: DeeType
Version: 0.3
Summary: A python package to classify data types from a list.
Home-page: https://github.com/Hardeepsingh980/DeeType.git
Author: Hardeep SIngh
Author-email: hardeep0khalsa122@gmail.com
License: MIT
Download-URL: https://github.com/Hardeepsingh980/DeeType/archive/master.zip
Keywords: Datatypes,classify,sort,datatypes,int,string,dict,list
Platform: UNKNOWN
Classifier: Development Status :: 5 - Production/Stable
Classifier: Intended Audience :: Developers
Classifier: Topic :: Software Development :: Build Tools
Classifier: License :: OSI Approved :: MIT License
Classifier: Programming Language :: Python :: 3
Classifier: Programming Language :: Python :: 3.4
Classifier: Programming Language :: Python :: 3.5
Classifier: Programming Language :: Python :: 3.6
